setup.py
CoreEngine/__init__.py
CoreEngine/dataadapter.py
CoreEngine/entity.py
CoreEngine/fontobjects.py
CoreEngine/loadingscreen.py
CoreEngine/maphandler.py
CoreEngine/musicplayer.py
CoreEngine/particles.py
CoreEngine/physics2D.py
CoreEngine/scenecontroller.py
CoreEngine/scenes.py
CoreEngine/spritesheetcreator.py
CoreEngine/staticobject.py
CoreEngine/template.py
CoreEngine/tile.py
CoreEngine/utility.py
CoreEngine/videoplayer.py
CoreEngine.egg-info/PKG-INFO
CoreEngine.egg-info/SOURCES.txt
CoreEngine.egg-info/dependency_links.txt
CoreEngine.egg-info/requires.txt
CoreEngine.egg-info/top_level.txt