Metadata-Version: 1.0
Name: CoreEngine
Version: 0.0.0.11
Summary: Pygame GameEngine
Home-page: UNKNOWN
Author: CoreTaxxe
Author-email: UNKNOWN
License: UNKNOWN
Platform: UNKNOWN
